diffino/__init__.py
diffino/cli.py
diffino/constants.py
diffino/exceptions.py
diffino/models.py
diffino-0.2.1.dist-info/LICENSE
diffino-0.2.1.dist-info/METADATA
diffino-0.2.1.dist-info/WHEEL
diffino-0.2.1.dist-info/entry_points.txt
diffino-0.2.1.dist-info/top_level.txt
diffino-0.2.1.dist-info/RECORD
