Metadata-Version: 2.1
Name: diffino
Version: 0.2.1
Summary: Diffing tools for comparing datasets in CSV, XLSX and other formats
Home-page: https://github.com/IntuitiveWebSolutions/diffino
Author: BriteCore
License: UNKNOWN
Keywords: diffing comparing csv excel json
Platform: UNKNOWN
Requires-Dist: pandas (==0.19.2)
Requires-Dist: boto3 (==1.7.3)
